{"custom_columns":{"c1":"Buildings in M-MP per damage state","c2":"Buildings in M-PCP3 per damage state","c3":"Buildings in M-PN per damage state","c4":"Buildings in M-PCP2 per damage state","c5":"Buildings in M-PCP1-T2 per damage state","c6":"Buildings in M-PCP1-T1 per damage state"},"loss_unit":"USD","total":{"loss_value":0,"cum_loss":972663987.7035036,"transition_matrix_from_damage_state":{},"buildings_by_damage_state":{"0":851551.0350562703,"1":642665.9479376187,"2":118693.02824869067,"3":19524.35568719952,"4":2953.63308693515}},"cum_loss_unit":"USD"}