{"custom_columns":{"c1":"Buildings in M-MP per damage state","c2":"Buildings in M-PCP3 per damage state","c3":"Buildings in M-PN per damage state","c4":"Buildings in M-PCP2 per damage state","c5":"Buildings in M-PCP1-T2 per damage state","c6":"Buildings in M-PCP1-T1 per damage state","c7":"Transitions from damage state 0","c8":"Transitions from damage state 1","c9":"Transitions from damage state 2","c10":"Transitions from damage state 3"},"loss_unit":"USD","total":{"loss_value":11731837.034461962,"cum_loss":943861454.2773173,"transition_matrix_from_damage_state":{"0":{"1":48.757568857087755,"2":69.6151851463544,"3":78.68555170459061,"4":110.94064530672998},"1":{"2":21.065772653853394,"3":22.11614302929791,"4":276.7671522801157},"2":{"3":3.7591091688418823,"4":102.85820260724022},"3":{"4":22.484981946207593}},"buildings_by_damage_state":{"0":848549.9308502256,"1":650260.2257129207,"2":115050.68087190946,"3":18281.24460091216,"4":3245.9179808951794}},"cum_loss_unit":"USD"}